enough_cards/__init__.py
enough_cards/_modidx.py
enough_cards/card.py
enough_cards/deck.py
nbdev_cards/__init__.py
nbdev_cards/_modidx.py
nbdev_cards/card.py
nbdev_cards/deck.py
nbs/__init__.py
enough_cards-0.0.2.dist-info/LICENSE
enough_cards-0.0.2.dist-info/METADATA
enough_cards-0.0.2.dist-info/WHEEL
enough_cards-0.0.2.dist-info/entry_points.txt
enough_cards-0.0.2.dist-info/top_level.txt
enough_cards-0.0.2.dist-info/RECORD
